liniarote/__init__.py
liniarote/cli.py
liniarote/config.py
liniarote-0.3.29.dist-info/LICENSE
liniarote-0.3.29.dist-info/METADATA
liniarote-0.3.29.dist-info/WHEEL
liniarote-0.3.29.dist-info/entry_points.txt
liniarote-0.3.29.dist-info/top_level.txt
liniarote-0.3.29.dist-info/RECORD
