Metadata-Version: 2.1
Name: liniarote
Version: 0.3.29
Summary: The Liniarote package is a command-line interface for the Liniarote programming language, for use in performing operations in transvalent mathematics (i.e., in which division by zero is permitted and generates predictable results, displayed with the aid of the transvalent number symbol “Ƿ”).
Home-page: https://github.com/NeuraXenetica/liniarote
Author: Matthew E. Gladden
Author-email: "Matthew E. Gladden" <matthew.gladden@neuraxenetica.com>
Maintainer: Matthew E. Gladden
Project-URL: Homepage, https://github.com/NeuraXenetica/liniarote
Project-URL: Bug Tracker, https://github.com/NeuraXenetica/liniarote/issues
Classifier: Programming Language :: Python :: 3
Classifier: License :: OSI Approved :: GNU General Public License v3 (GPLv3)
Classifier: Operating System :: Microsoft :: Windows
Requires-Python: >=3.9
License-File: LICENSE
Requires-Dist: readchar
Requires-Dist: sly
